Metadata-Version: 1.1
Name: openwrt-ubus-rpc
Version: 0.0.3
Summary: OpenWrt ubus RPC API library
Home-page: https://github.com/Noltari/python-ubus-rpc
Author: noltari
Author-email: noltari@gmail.com
License: GPL2
Keywords: api,openwrt,ubus
Platform: any
Classifier: Development Status :: 2 - Pre-Alpha
Classifier: Topic :: Home Automation
Classifier: Intended Audience :: Developers
Classifier: License :: OSI Approved :: GNU General Public License v2 (GPLv2)
Classifier: Natural Language :: English
Classifier: Programming Language :: Python :: 3
Classifier: Programming Language :: Python :: 3.8
Classifier: Programming Language :: Python :: 3.9
